data/web.conllu
data/wiki.conllu
turkish_treebanks/__init__.py
turkish_treebanks/read.py
turkish_treebanks/twt_pb2.py
turkish_treebanks-1.0.0.dist-info/LICENSE
turkish_treebanks-1.0.0.dist-info/METADATA
turkish_treebanks-1.0.0.dist-info/WHEEL
turkish_treebanks-1.0.0.dist-info/top_level.txt
turkish_treebanks-1.0.0.dist-info/RECORD
